{
  "year": 2021,
  "importedAt": "2026-02-13T22:28:50.961Z",
  "totalFiles": 6,
  "successful": 6,
  "failed": 0,
  "documents": [
    {
      "id": "doc_mllglpp9_6k4gt5",
      "sourcePath": "/Users/bethcartrette/Library/CloudStorage/GoogleDrive-beth@bethcnc.com/My Drive/Health/MEDICAL RECORDS BY YEAR/2021/GP/12_Dec 16 2021_Dr Starr/T#.pdf",
      "fileName": "T#.pdf",
      "year": 2021,
      "specialty": "primary_care",
      "type": "lab_single",
      "eventDate": "2021-12-16",
      "provider": "Eric Starr",
      "facility": "Novant Health",
      "fullText": "10/25/24, 9:10 PM MyAtriumHealth - Test Details\nName: Beth Cartrette | DOB: 9/13/1982 | MRN: 4179018 | PCP: Timothy P Kennard, MD | Legal Name: Jennifer Beth Cartrette\nT3\nCollected on December 16, 2021 12:44 PM\nNovant Health\nEric Starr 12/19/2021, 8:51 PM\nHello:\nYour labs have returned\nTSH, is normal at your thyroid-stimulating hormone your\nantibodies for thyroid one of them has now normal and one is\nstill elevated but has improved, the remainder of your labs are\nnormal CBC shows no evidence of anemia or infection normal\nblood sugar kidney and liver function arthritis panel for lupus\nand rheumatoid arthritis and gout were normal\nYou do have a referral being worked on for pain management\nPlease don't hesitate to call or e-mail with questions or concerns\nEric Starr PA-C\nResults\nPerformed at: 01 - Labcorp Burlington\n1447 York Court, Burlington, NC 272153361\nLab Director: Sanjai Nagendra MD, Phone: 8007624344\nT3, Total\nNormal range: 71 - 180 ng/dL\n112\n71 180\nAuthorizing provider: Eric Starr\nCollection date: December 16, 2021 12:44 PM\nSpecimens: Blood\nResult date: December 17, 2021 2:36 PM\nhttps://my.atriumhealth.org/myatriumhealth/app/test-results/details?pageMode=1&eorderid=WP-24J6RAMT-2BCJTkvkrZlSAbhag-3D-3D-24lfAKTjTJuE0yyg2sZM… 1/2\n\n--- PAGE BREAK ---\n\n10/25/24, 9:10 PM MyAtriumHealth - Test Details\nResult status: Final\nResulting lab:\nLABCORP\nMyChart® licensed from Epic Systems Corporation© 1999 - 2024\nhttps://my.atriumhealth.org/myatriumhealth/app/test-results/details?pageMode=1&eorderid=WP-24J6RAMT-2BCJTkvkrZlSAbhag-3D-3D-24lfAKTjTJuE0yyg2sZM… 2/2",
      "pageCount": 2,
      "fileSizeBytes": 55105,
      "extractedAt": "2026-02-13T22:28:35.805Z",
      "classificationConfidence": 1,
      "diagnoses": [],
      "medications": [],
      "procedures": [],
      "labResults": [
        {
          "test": "T3, Total",
          "value": "112",
          "unit": "ng/dL",
          "reference": "71 - 180 ng/dL"
        }
      ],
      "keyFindings": [
        "TSH, is normal",
        "antibodies for thyroid one of them has now normal and one is still elevated but has improved",
        "CBC shows no evidence of anemia or infection",
        "normal blood sugar",
        "kidney and liver function normal",
        "arthritis panel for lupus and rheumatoid arthritis and gout were normal",
        "You do have a referral being worked on for pain management"
      ]
    },
    {
      "id": "doc_mllgls46_mbgycz",
      "sourcePath": "/Users/bethcartrette/Library/CloudStorage/GoogleDrive-beth@bethcnc.com/My Drive/Health/MEDICAL RECORDS BY YEAR/2021/GP/12_Dec 16 2021_Dr Starr/T4.pdf",
      "fileName": "T4.pdf",
      "year": 2021,
      "specialty": "primary_care",
      "type": "lab_single",
      "eventDate": "2021-12-16",
      "provider": "Eric Starr",
      "facility": "Novant Health",
      "fullText": "10/25/24, 9:10 PM MyAtriumHealth - Test Details\nName: Beth Cartrette | DOB: 9/13/1982 | MRN: 4179018 | PCP: Timothy P Kennard, MD | Legal Name: Jennifer Beth Cartrette\nT4\nCollected on December 16, 2021 12:44 PM\nNovant Health\nEric Starr 12/19/2021, 8:51 PM\nHello:\nYour labs have returned\nTSH, is normal at your thyroid-stimulating hormone your\nantibodies for thyroid one of them has now normal and one is\nstill elevated but has improved, the remainder of your labs are\nnormal CBC shows no evidence of anemia or infection normal\nblood sugar kidney and liver function arthritis panel for lupus\nand rheumatoid arthritis and gout were normal\nYou do have a referral being worked on for pain management\nPlease don't hesitate to call or e-mail with questions or concerns\nEric Starr PA-C\nResults\nPerformed at: 01 - Labcorp Burlington\n1447 York Court, Burlington, NC 272153361\nLab Director: Sanjai Nagendra MD, Phone: 8007624344\nT4, Total\nNormal range: 4.5 - 12.0 ug/dL\n7.6\n4.5 12\nAuthorizing provider: Eric Starr\nCollection date: December 16, 2021 12:44 PM\nSpecimens: Blood\nResult date: December 17, 2021 2:36 PM\nhttps://my.atriumhealth.org/myatriumhealth/app/test-results/details?pageMode=1&eorderid=WP-24sxhC5TQxiLzyEmt4sOdoDg-3D-3D-24XpnGa55thJGiVCr2VCV… 1/2\n\n--- PAGE BREAK ---\n\n10/25/24, 9:10 PM MyAtriumHealth - Test Details\nResult status: Final\nResulting lab:\nLABCORP\nMyChart® licensed from Epic Systems Corporation© 1999 - 2024\nhttps://my.atriumhealth.org/myatriumhealth/app/test-results/details?pageMode=1&eorderid=WP-24sxhC5TQxiLzyEmt4sOdoDg-3D-3D-24XpnGa55thJGiVCr2VCV… 2/2",
      "pageCount": 2,
      "fileSizeBytes": 54645,
      "extractedAt": "2026-02-13T22:28:38.934Z",
      "classificationConfidence": 1,
      "diagnoses": [],
      "medications": [],
      "procedures": [],
      "labResults": [
        {
          "test": "T4, Total",
          "value": "7.6",
          "unit": "ug/dL",
          "reference": "4.5 - 12.0 ug/dL"
        }
      ],
      "keyFindings": [
        "TSH, is normal",
        "antibodies for thyroid one of them has now normal and one is still elevated but has improved",
        "CBC shows no evidence of anemia or infection",
        "normal blood sugar",
        "kidney and liver function",
        "arthritis panel for lupus and rheumatoid arthritis and gout were normal"
      ]
    },
    {
      "id": "doc_mllgluar_2vzf4h",
      "sourcePath": "/Users/bethcartrette/Library/CloudStorage/GoogleDrive-beth@bethcnc.com/My Drive/Health/MEDICAL RECORDS BY YEAR/2021/GP/12_Dec 16 2021_Dr Starr/THYROGLOBULIN ANTIBODY.pdf",
      "fileName": "THYROGLOBULIN ANTIBODY.pdf",
      "year": 2021,
      "specialty": "primary_care",
      "type": "lab_single",
      "eventDate": "2021-12-16",
      "provider": "Eric Starr PA-C",
      "facility": "Novant Health",
      "fullText": "10/25/24, 9:11 PM MyAtriumHealth - Test Details\nName: Beth Cartrette | DOB: 9/13/1982 | MRN: 4179018 | PCP: Timothy P Kennard, MD | Legal Name: Jennifer Beth Cartrette\nTHYROGLOBULIN ANTIBODY\nCollected on December 16, 2021 12:44 PM\nNovant Health\nEric Starr 12/19/2021, 8:51 PM\nHello:\nYour labs have returned\nTSH, is normal at your thyroid-stimulating hormone your\nantibodies for thyroid one of them has now normal and one is\nstill elevated but has improved, the remainder of your labs are\nnormal CBC shows no evidence of anemia or infection normal\nblood sugar kidney and liver function arthritis panel for lupus\nand rheumatoid arthritis and gout were normal\nYou do have a referral being worked on for pain management\nPlease don't hesitate to call or e-mail with questions or concerns\nEric Starr PA-C\nResults\nPerformed at: 01 - Labcorp Burlington\n1447 York Court, Burlington, NC 272153361\nLab Director: Sanjai Nagendra MD, Phone: 8007624344\nThyroglobulin Ab\nNormal range: 0.0 - 0.9 IU/mL\nValue\n<1.0\nThyroglobulin Antibody measured by Beckman Coulter Methodology\nAuthorizing provider: Eric Starr\nCollection date: December 16, 2021 12:44 PM\nSpecimens: Blood\nResult date: December 17, 2021 2:36 PM\nhttps://my.atriumhealth.org/myatriumhealth/app/test-results/details?pageMode=1&eorderid=WP-24wEx1UYvA5HFx8jLa9AVbFQ-3D-3D-24nMTFqGW-2Fxz1vuSL… 1/2\n\n--- PAGE BREAK ---\n\n10/25/24, 9:11 PM MyAtriumHealth - Test Details\nResult status: Final\nResulting lab:\nLABCORP\nMyChart® licensed from Epic Systems Corporation© 1999 - 2024\nhttps://my.atriumhealth.org/myatriumhealth/app/test-results/details?pageMode=1&eorderid=WP-24wEx1UYvA5HFx8jLa9AVbFQ-3D-3D-24nMTFqGW-2Fxz1vuSL… 2/2",
      "pageCount": 2,
      "fileSizeBytes": 54275,
      "extractedAt": "2026-02-13T22:28:41.763Z",
      "classificationConfidence": 1,
      "diagnoses": [],
      "medications": [],
      "procedures": [],
      "labResults": [
        {
          "test": "Thyroglobulin Ab",
          "value": "<1.0",
          "unit": "IU/mL",
          "reference": "0.0 - 0.9 IU/mL"
        }
      ],
      "keyFindings": [
        "TSH, is normal",
        "antibodies for thyroid one of them has now normal and one is still elevated but has improved",
        "CBC shows no evidence of anemia or infection",
        "normal blood sugar",
        "kidney and liver function",
        "arthritis panel for lupus and rheumatoid arthritis and gout were normal",
        "You do have a referral being worked on for pain management"
      ]
    },
    {
      "id": "doc_mllglw8l_ww2vhb",
      "sourcePath": "/Users/bethcartrette/Library/CloudStorage/GoogleDrive-beth@bethcnc.com/My Drive/Health/MEDICAL RECORDS BY YEAR/2021/GP/12_Dec 16 2021_Dr Starr/THYROID PEROXIDASE AB.pdf",
      "fileName": "THYROID PEROXIDASE AB.pdf",
      "year": 2021,
      "specialty": "primary_care",
      "type": "lab_single",
      "eventDate": "2021-12-16",
      "provider": "Eric Starr",
      "facility": "Novant Health",
      "fullText": "10/25/24, 9:11 PM MyAtriumHealth - Test Details\nName: Beth Cartrette | DOB: 9/13/1982 | MRN: 4179018 | PCP: Timothy P Kennard, MD | Legal Name: Jennifer Beth Cartrette\nTHYROID PEROXIDASE AB\nCollected on December 16, 2021 12:44 PM\nNovant Health\nEric Starr 12/19/2021, 8:51 PM\nHello:\nYour labs have returned\nTSH, is normal at your thyroid-stimulating hormone your\nantibodies for thyroid one of them has now normal and one is\nstill elevated but has improved, the remainder of your labs are\nnormal CBC shows no evidence of anemia or infection normal\nblood sugar kidney and liver function arthritis panel for lupus\nand rheumatoid arthritis and gout were normal\nYou do have a referral being worked on for pain management\nPlease don't hesitate to call or e-mail with questions or concerns\nEric Starr PA-C\nResults\nPerformed at: 01 - Labcorp Burlington\n1447 York Court, Burlington, NC 272153361\nLab Director: Sanjai Nagendra MD, Phone: 8007624344\nThyroid Peroxidase Ab\nNormal range: 0 - 34 IU/mL\n44\n0 34\nAuthorizing provider: Eric Starr\nCollection date: December 16, 2021 12:44 PM\nSpecimens: Blood\nResult date: December 17, 2021 2:36 PM\nhttps://my.atriumhealth.org/myatriumhealth/app/test-results/details?pageMode=1&eorderid=WP-24fBsh8taMrPPG29rBgYxFAA-3D-3D-24ZsBg8BYu2S-2BIGBA1y… 1/2\n\n--- PAGE BREAK ---\n\n10/25/24, 9:11 PM MyAtriumHealth - Test Details\nResult status: Final\nResulting lab:\nLABCORP\nMyChart® licensed from Epic Systems Corporation© 1999 - 2024\nhttps://my.atriumhealth.org/myatriumhealth/app/test-results/details?pageMode=1&eorderid=WP-24fBsh8taMrPPG29rBgYxFAA-3D-3D-24ZsBg8BYu2S-2BIGBA1y… 2/2",
      "pageCount": 2,
      "fileSizeBytes": 55259,
      "extractedAt": "2026-02-13T22:28:44.277Z",
      "classificationConfidence": 1,
      "diagnoses": [],
      "medications": [],
      "procedures": [],
      "labResults": [
        {
          "test": "Thyroid Peroxidase Ab",
          "value": "44",
          "unit": "IU/mL",
          "reference": "0 - 34 IU/mL"
        }
      ],
      "keyFindings": [
        "TSH, is normal",
        "antibodies for thyroid one of them has now normal and one is still elevated but has improved",
        "CBC shows no evidence of anemia or infection",
        "normal blood sugar",
        "kidney and liver function",
        "arthritis panel for lupus and rheumatoid arthritis and gout were normal"
      ]
    },
    {
      "id": "doc_mllglys4_cizmyb",
      "sourcePath": "/Users/bethcartrette/Library/CloudStorage/GoogleDrive-beth@bethcnc.com/My Drive/Health/MEDICAL RECORDS BY YEAR/2021/GP/12_Dec 16 2021_Dr Starr/TSH.pdf",
      "fileName": "TSH.pdf",
      "year": 2021,
      "specialty": "primary_care",
      "type": "lab_single",
      "eventDate": "2021-12-16",
      "provider": "Eric Starr",
      "facility": "Novant Health",
      "fullText": "10/25/24, 9:09 PM MyAtriumHealth - Test Details\nName: Beth Cartrette | DOB: 9/13/1982 | MRN: 4179018 | PCP: Timothy P Kennard, MD | Legal Name: Jennifer Beth Cartrette\nTSH\nCollected on December 16, 2021 12:44 PM\nNovant Health\nEric Starr 12/19/2021, 8:51 PM\nHello:\nYour labs have returned\nTSH, is normal at your thyroid-stimulating hormone your\nantibodies for thyroid one of them has now normal and one is\nstill elevated but has improved, the remainder of your labs are\nnormal CBC shows no evidence of anemia or infection normal\nblood sugar kidney and liver function arthritis panel for lupus\nand rheumatoid arthritis and gout were normal\nYou do have a referral being worked on for pain management\nPlease don't hesitate to call or e-mail with questions or concerns\nEric Starr PA-C\nResults\nPerformed at: 01 - Labcorp Burlington\n1447 York Court, Burlington, NC 272153361\nLab Director: Sanjai Nagendra MD, Phone: 8007624344\nTSH\nNormal range: 0.450 - 4.500 uIU/mL\n4.440\n0.45 4.5\nAuthorizing provider: Eric Starr\nCollection date: December 16, 2021 12:44 PM\nSpecimens: Blood\nResult date: December 17, 2021 2:36 PM\nhttps://my.atriumhealth.org/myatriumhealth/app/test-results/details?pageMode=1&eorderid=WP-24iUd6XMl49s1aofHzIO527A-3D-3D-247PeLiyaqLpcCoygv4Hqs0… 1/2\n\n--- PAGE BREAK ---\n\n10/25/24, 9:09 PM MyAtriumHealth - Test Details\nResult status: Final\nResulting lab:\nLABCORP\nMyChart® licensed from Epic Systems Corporation© 1999 - 2024\nhttps://my.atriumhealth.org/myatriumhealth/app/test-results/details?pageMode=1&eorderid=WP-24iUd6XMl49s1aofHzIO527A-3D-3D-247PeLiyaqLpcCoygv4Hqs0… 2/2",
      "pageCount": 2,
      "fileSizeBytes": 54014,
      "extractedAt": "2026-02-13T22:28:47.572Z",
      "classificationConfidence": 1,
      "diagnoses": [],
      "medications": [],
      "procedures": [],
      "labResults": [
        {
          "test": "TSH",
          "value": "4.440",
          "unit": "uIU/mL",
          "reference": "0.450 - 4.500 uIU/mL"
        }
      ],
      "keyFindings": [
        "TSH, is normal at your thyroid-stimulating hormone",
        "antibodies for thyroid one of them has now normal and one is still elevated but has improved",
        "CBC shows no evidence of anemia or infection",
        "normal blood sugar kidney and liver function",
        "arthritis panel for lupus and rheumatoid arthritis and gout were normal",
        "You do have a referral being worked on for pain management"
      ]
    },
    {
      "id": "doc_mllgm1e9_9oxy90",
      "sourcePath": "/Users/bethcartrette/Library/CloudStorage/GoogleDrive-beth@bethcnc.com/My Drive/Health/MEDICAL RECORDS BY YEAR/2021/GP/12_Dec 16 2021_Dr Starr/URIC A+ESR-WES+ANA+RA QN .pdf",
      "fileName": "URIC A+ESR-WES+ANA+RA QN .pdf",
      "year": 2021,
      "specialty": "primary_care",
      "type": "lab_panel",
      "eventDate": "2021-12-16",
      "provider": "Eric Starr PA-C",
      "facility": "Novant Health",
      "fullText": "10/25/24, 9:10 PM MyAtriumHealth - Test Details\nName: Beth Cartrette | DOB: 9/13/1982 | MRN: 4179018 | PCP: Timothy P Kennard, MD | Legal Name: Jennifer Beth Cartrette\nURIC A+ESR-WES+ANA+RA QN\nCollected on December 16, 2021 12:44 PM\nNovant Health\nEric Starr 12/19/2021, 8:51 PM\nHello:\nYour labs have returned\nTSH, is normal at your thyroid-stimulating hormone your\nantibodies for thyroid one of them has now normal and one is\nstill elevated but has improved, the remainder of your labs are\nnormal CBC shows no evidence of anemia or infection normal\nblood sugar kidney and liver function arthritis panel for lupus\nand rheumatoid arthritis and gout were normal\nYou do have a referral being worked on for pain management\nPlease don't hesitate to call or e-mail with questions or concerns\nEric Starr PA-C\nResults\nPerformed at: 01 - Labcorp Burlington\n1447 York Court, Burlington, NC 272153361\nLab Director: Sanjai Nagendra MD, Phone: 8007624344\nUric Acid ANA Direct\nNormal range: 2.6 - 6.2 mg/dL Normal value: Negative\n3.4\nValue\nNegative\n2.6 6.2\nTherapeutic target for gout patients: <6.0\nhttps://my.atriumhealth.org/myatriumhealth/app/test-results/details?pageMode=1&eorderid=WP-249IukWcVG-2BNmqBlWSgA4UrQ-3D-3D-24Z8fYYFdnd6AwjL… 1/2\n\n--- PAGE BREAK ---\n\n10/25/24, 9:10 PM MyAtriumHealth - Test Details\nRA Quant Sed Rate\nNormal value: <14.0 IU/mL Normal range: 0 - 32 mm/hr\n6\nValue\n10.7\n0 32\nAuthorizing provider: Eric Starr\nCollection date: December 16, 2021 12:44 PM\nSpecimens: Blood\nResult date: December 17, 2021 2:36 PM\nResult status: Final\nResulting lab:\nLABCORP\nMyChart® licensed from Epic Systems Corporation© 1999 - 2024\nhttps://my.atriumhealth.org/myatriumhealth/app/test-results/details?pageMode=1&eorderid=WP-249IukWcVG-2BNmqBlWSgA4UrQ-3D-3D-24Z8fYYFdnd6AwjL… 2/2",
      "pageCount": 2,
      "fileSizeBytes": 67417,
      "extractedAt": "2026-02-13T22:28:50.961Z",
      "classificationConfidence": 1,
      "diagnoses": [],
      "medications": [],
      "procedures": [],
      "labResults": [
        {
          "test": "Uric Acid",
          "value": "3.4",
          "unit": "mg/dL",
          "reference": "2.6 - 6.2"
        },
        {
          "test": "ANA Direct",
          "value": "Negative",
          "unit": "",
          "reference": "Negative"
        },
        {
          "test": "RA Quant",
          "value": "6",
          "unit": "IU/mL",
          "reference": "<14.0"
        },
        {
          "test": "Sed Rate",
          "value": "10.7",
          "unit": "mm/hr",
          "reference": "0 - 32"
        }
      ],
      "keyFindings": [
        "TSH is normal",
        "antibodies for thyroid one of them has now normal and one is still elevated but has improved",
        "CBC shows no evidence of anemia or infection",
        "normal blood sugar",
        "kidney and liver function normal",
        "arthritis panel for lupus and rheumatoid arthritis and gout were normal"
      ]
    }
  ],
  "errors": [],
  "bySpecialty": {
    "primary_care": 6
  },
  "byType": {
    "lab_single": 5,
    "lab_panel": 1
  }
}