{
  "year": 2019,
  "importedAt": "2026-02-13T22:26:26.506Z",
  "totalFiles": 2,
  "successful": 2,
  "failed": 0,
  "documents": [
    {
      "id": "doc_mllgiuy6_02fh8a",
      "sourcePath": "/Users/bethcartrette/Library/CloudStorage/GoogleDrive-beth@bethcnc.com/My Drive/Health/MEDICAL RECORDS BY YEAR/2019/GP/10_Oct 18_2019_Dr Starr/XR WRIST 3+ VIEWS LEFT.pdf",
      "fileName": "XR WRIST 3+ VIEWS LEFT.pdf",
      "year": 2019,
      "specialty": "primary_care",
      "type": "imaging_xray",
      "eventDate": "2019-10-18",
      "provider": "Richard Dunlop, MD",
      "facility": "Novant Health",
      "fullText": "10/25/24, 8:58 PM MyAtriumHealth - Test Details\nName: Beth Cartrette | DOB: 9/13/1982 | MRN: 4179018 | PCP: Timothy P Kennard, MD | Legal Name: Jennifer Beth Cartrette\nXR WRIST 3+ VIEWS LEFT\nCollected on October 18, 2019 11:04 AM\nNovant Health\nEric Starr 10/18/2019, 1:11 PM\nHello:\nX-ray was read by the radiologist and showed no acute\nabnormality, please continue recommendations from office visit\nand let us know if not improving\nLet us know if you have any questions or concerns\nSincerely\nEric Starr PA-C\nResults\nImpression\nIMPRESSION:\n1. Mild so\u0000 tissue swelling about the radial side of the wrist.\n2. No fractures, dislocations, or significant degenerative changes.\nElectronically Signed by: Richard Dunlop, MD\nNarrative\nLe\u0000 wrist, 5 views\nComparison: None.\nAuthorizing provider: Eric Starr\nReading physician: Richard Dunlop\nStudy date: October 18, 2019 11:05 AM\nCollection date: October 18, 2019 11:04 AM\nResult date: October 18, 2019 11:05 AM\nResult status: Final\nhttps://my.atriumhealth.org/myatriumhealth/app/test-results/details?pageMode=1&eorderid=WP-24ZJDJlSWJv0dtToJRCHdxNA-3D-3D-24hXS-2FjO7LWBvHLUt7… 1/2\n\n--- PAGE BREAK ---\n\n10/25/24, 8:58 PM MyAtriumHealth - Test Details\nMyChart® licensed from Epic Systems Corporation© 1999 - 2024\nhttps://my.atriumhealth.org/myatriumhealth/app/test-results/details?pageMode=1&eorderid=WP-24ZJDJlSWJv0dtToJRCHdxNA-3D-3D-24hXS-2FjO7LWBvHLUt7… 2/2",
      "pageCount": 2,
      "fileSizeBytes": 46688,
      "extractedAt": "2026-02-13T22:26:22.638Z",
      "classificationConfidence": 1,
      "diagnoses": [],
      "medications": [],
      "procedures": [],
      "labResults": [],
      "keyFindings": [
        "Mild soft tissue swelling about the radial side of the wrist.",
        "No fractures, dislocations, or significant degenerative changes."
      ]
    },
    {
      "id": "doc_mllgixxm_5zxfld",
      "sourcePath": "/Users/bethcartrette/Library/CloudStorage/GoogleDrive-beth@bethcnc.com/My Drive/Health/MEDICAL RECORDS BY YEAR/2019/Hand Doc/11-26-2019_hand Doctor.pdf",
      "fileName": "11-26-2019_hand Doctor.pdf",
      "year": 2019,
      "specialty": "hand doc",
      "type": "office_visit",
      "eventDate": "2019-11-26",
      "provider": "Brandon J Valentine, M.D.",
      "facility": null,
      "fullText": "10/26/24, 5:54 AM MyChart - Visit Summary\nName: Jennifer Beth Cartrette | DOB: 9/13/1982 | MRN: 71030963 | PCP: Timothy Kennard, MD | Legal Name: Jennifer Beth\nCartrette\nAppointment Details\nNotes\nProgress Notes\nJames Vollmer at 11/26/19 0930\nAttestation signed by Brandon Valentine at 11/26/19 1035\nPatient seen in the office today, history reviewed, and examined.\nAgree with physician assistant recorded history and exam.\nThe presenting history and exam are most consistent with carpal tunnel syndrome. This\ncondition is reviewed at length in the office today.\nWe have discussed the etiology, pathophysiology, natural history, and treatment options\nfor this condition. I have explained that with progressive symptoms I recommend\nelectrodiagnostic testing to confirm the location and define the severity of any focal\ncompressive neuropathy.\nShe may be a candidate for carpal tunnel release to prevent any permanent or further\nloss of feeling and strength in the hand. We have discussed the surgical procedure for\ncarpal tunnel release in the office today as well, along with the risks and benefits.\nShe agrees to proceed with nerve study, and this is ordered today.\nFollow-up after nerve study.\nElectronically signed by Brandon J Valentine, M.D.\nChief Complaint:\n:\nChief Complaint\nPatient presents with\n• Numbness\nLeft Hand\nHistory of Present Illness:\nJennifer Beth Cartrette is a 37 y.o. female who presents today as a new patient to Dr. Valentine\nwith left hand pain as well as numbness and tingling. Patient reports near constant numbness\nand tingling over the past 2 weeks, with intermittent symptoms prior. States it is affecting the left\nhand significantly, most prevalent into the thumb index and middle finger. States that it actively\nwakes her up at night, despite bracing. Recent bracing has started to cause some improvement\nhttps://www.novantmychart.org/MyChart/inside.asp?mode=visitsummary&submode=notes&csn=WP-245IUCe07z0w-2FfjiT6KK1Inw-3D-3D-24z3EJJbfbea7OQ8J0… 1/6\n\n--- PAGE BREAK ---\n\n10/26/24, 5:54 AM MyChart - Visit Summary\nin symptoms. Did seek evaluation with primary care had x-rays taken in October which were\nnegative. Patient states that the numbness and pain is impacting activities of daily living and\nability to work as a manager of a restaurant. Patient did have prior spinal surgery with Dr.\nHartman, C456 and 7. States that the numbness did not happen following the surgery. Did have\na previous nerve study with Dr. Sue Huskey prior to the spinal surgery which was a normal study.\nPatient presents with\n• Numbness\nLeft Hand\nNo Known Allergies\nNo outpatient medications have been marked as taking for the 11/26/19 encounter\n(Office Visit) with Brandon J Valentine, MD.\nPast Medical History:\nDiagnosis Date\n• ADHD\n• Anorexia\n• Bipolar disorder (*)\n• Broken teeth\nupper left, lower right\n• Colitis age 25\nIschemic\n• Colon polyp 2005\nIschemic Colotis\n• DDD (degenerative disc disease), cervical\n• DDD (degenerative disc disease), cervical\n• Dental crowns present\n• Disease of thyroid gland\ngrave's disease\n• Eating disorder Childhood\nIn remission\n• Presence of dental prosthetic device\nRight lower x1\n• PTSD (post-traumatic stress disorder)\n• Teeth missing\nPast Surgical History:\nProcedure Laterality Date\n• Sinus surgery 2008\n• Spinal fusion\nSocial History\nSocioeconomic History\n• Marital status: Significant Other\nSpouse name: Not on file\n• Number of children: 0\n• Years of education: Not on file\n• Highest education level: Not on file\nOccupational History\n• Occupation: front house - of restaurant\nSocial Needs\n• Financial resource strain: Not on file\n• Food insecurity\nWorry: Not on file\nInability: Not on file\n• Transportation needs\nMedical: Not on file\nhttps://www.novantmychart.org/MyChart/inside.asp?mode=visitsummary&submode=notes&csn=WP-245IUCe07z0w-2FfjiT6KK1Inw-3D-3D-24z3EJJbfbea7OQ8J0… 2/6\n\n--- PAGE BREAK ---\n\n10/26/24, 5:54 AM MyChart - Visit Summary\nNon-medical: Not on file\nTobacco Use\n• Smoking status: Former Smoker\nPacks/day: 0.00\nStart date: 1/1/2000\nLast attempt to quit: 1/1/2013\nYears since quitting: 6.9\n• Smokeless tobacco: Never Used\n• Tobacco comment: Quit- age 30\nSubstance and Sexual Activity\n• Alcohol use: Yes\nComment: rarely\n• Drug use: Yes\nTypes: Marijuana\nComment: last used - 2 to 3 yrs. ago\n• Sexual activity: Yes\nPartners: Male\nBirth control/protection: None\nLifestyle\n• Physical activity\nDays per week: Not on file\nMinutes per session: Not on file\n• Stress: Not on file\nRelationships\n• Social connections\nTalks on phone: Not on file\nGets together: Not on file\nAttends religious Not on file\nservice:\nActive member of club Not on file\nor organization:\nAttends meetings of Not on file\nclubs or organizations:\nRelationship status: Not on file\n• Intimate partner violence\nFear of current or ex Not on file\npartner:\nEmotionally abused: Not on file\nPhysically abused: Not on file\nForced sexual activity: Not on file\nOther Topics Concern\n• Not on file\nSocial History Narrative\n• Not on file\nFamily History\nProblem Relation Age of Onset\n• Stroke Father\n• Bipolar disorder Father\n• Anxiety disorder Father\n• ADD / ADHD Father\n• Thyroid disease Maternal Grandmother\n• Thyroid disease Maternal Aunt\n• Stroke Maternal Grandfather\n• Stroke Paternal Grandfather\n• ADD / ADHD Sister\n• ADD / ADHD Brother\n• Anxiety disorder Paternal Uncle\n• Depression Paternal Uncle\n• Stroke Paternal Grandmother\n• Cancer Neg Hx\nhttps://www.novantmychart.org/MyChart/inside.asp?mode=visitsummary&submode=notes&csn=WP-245IUCe07z0w-2FfjiT6KK1Inw-3D-3D-24z3EJJbfbea7OQ8J0… 3/6\n\n--- PAGE BREAK ---\n\n10/26/24, 5:54 AM MyChart - Visit Summary\n• Breast cancer Neg Hx\n• Colon cancer Neg Hx\n• Diabetes Neg Hx\n• Hypertension Neg Hx\nPast Medical History, Past Surgery History, Allergies, Social History, and Family History\nwere reviewed and updated.\nReview of Systems\nComprehensive review of systems is performed and is negative except positive for\nChief Complaint\nPatient presents with\n• Numbness\nLeft Hand\nObjective\nVitals:\n11/26/19 0919\nBP: 122/84\nPulse: 106\nPhysical exam\nGeneral Appearance: Appears Stated Age, Well-Nourished; Oriented x 3; Gait: Ambulating\nwithout a limp; Eyes are clear, pupils symmetric and reactive to light; Skin: no lesions, no\nerythema; Neck: no thyroid enlargement, no jugular venous distension; heart: Regular rate and\nrhythm, lungs: Clear to auscultation bilaterally\nAlert, oriented, pleasant, and cooperative.\nSkin is intact with no rashes, blemishes, or lesions.\nSensibility and perfusion are intact throughout the digits\nOn examination today patient maintains full composite fist. Full digital range of motion. Full\nrange of motion of the wrist\nNontender to palpation along the flexor tendon in all digits are near the A1 pulley\nPositive Erkins of the left carpal tunnel, APB motor function intact\nNegative Tinel's over the cubital tunnel, no intrinsic wasting\nWatson's and provocative maneuvers negative for carpal instability\nNegative Finkelstein\nNegative thumb CMC grind\notherwise neurovascular examination grossly intact\nPA lateral and oblique x-rays of the left wrist dated 10/18/2019 reviewed today by Dr. Valentine.\nX-rays negative for fracture\nImpression\n1. Left hand paresthesia\n2. Left hand pain\nL NCS with cervicals\nhttps://www.novantmychart.org/MyChart/inside.asp?mode=visitsummary&submode=notes&csn=WP-245IUCe07z0w-2FfjiT6KK1Inw-3D-3D-24z3EJJbfbea7OQ8J0… 4/6\n\n--- PAGE BREAK ---\n\n10/26/24, 5:54 AM MyChart - Visit Summary\nPlan\nPatient seen and evaluated by Dr Valentine and seen and dictated by James Vollmer PA-C\nSee attestation from Dr Valentine for plan\nPortions of this note were dictated using Dragon software. It has been reviewed for accuracy but\nmay contain grammatical and clerical errors. If there are any questions, please feel free to contact\nme at 704-365-6730\nPatient's Medications\nAccurate as of November 26, 2019 9:30 AM. Reflects encounter med changes as\nof last refresh\nContinued Medications\nInstructions\nacetaminophen 325 mg tablet 650 mg, Oral, Every 6 hours as needed, Take 3\nCommonly known as: TYLENOL tablets prn\n* amphetamine- 20 mg, Oral, 3 times a day\ndextroamphetamine 20 MG tablet\nCommonly known as: ADDERALL\nStart taking on: December 14, 2019\n* amphetamine- 20 mg, Oral, 3 times a day\ndextroamphetamine 20 MG tablet\nCommonly known as: ADDERALL\nStart taking on: January 13, 2020\n* amphetamine- 20 mg, Oral, 3 times a day\ndextroamphetamine 20 MG tablet\nCommonly known as: ADDERALL\nStart taking on: February 11, 2020\nARIPiprazole 10 mg tablet 10 mg, Oral, Daily, Take 1/2 tab daily for 7 days,\nCommonly known as: ABILIFY then 1 tab daily thereafter.\nNaproxen-Esomeprazole 500-20 1 tablet, Oral, 2 times a day\nMG Tbec per DR tablet\nCommonly known as: VIMOVO\n* This list has 3 medication(s) that are the same as other medications\nprescribed for you. Read the directions carefully, and ask your doctor or other\ncare provider to review them with you.\nNo orders of the defined types were placed in this encounter.\nThere are no Patient Instructions on file for this visit.\nNo follow-ups on file.\nhttps://www.novantmychart.org/MyChart/inside.asp?mode=visitsummary&submode=notes&csn=WP-245IUCe07z0w-2FfjiT6KK1Inw-3D-3D-24z3EJJbfbea7OQ8J0… 5/6\n\n--- PAGE BREAK ---\n\n10/26/24, 5:54 AM MyChart - Visit Summary\nI will be happy to see them back at any point in time regarding this or any other issue that may\narise.\nCc: Gina G LiCause, MD\nMyChart® licensed from Epic Systems Corporation © 1999 - 2024\nhttps://www.novantmychart.org/MyChart/inside.asp?mode=visitsummary&submode=notes&csn=WP-245IUCe07z0w-2FfjiT6KK1Inw-3D-3D-24z3EJJbfbea7OQ8J0… 6/6",
      "pageCount": 6,
      "fileSizeBytes": 419192,
      "extractedAt": "2026-02-13T22:26:26.506Z",
      "classificationConfidence": 1,
      "diagnoses": [
        "carpal tunnel syndrome",
        "Left hand paresthesia",
        "Left hand pain"
      ],
      "medications": [
        "acetaminophen 325 mg tablet 650 mg, Oral, Every 6 hours as needed, Take 3",
        "amphetamine- 20 mg, Oral, 3 times a day",
        "dextroamphetamine 20 MG tablet",
        "ARIPiprazole 10 mg tablet 10 mg, Oral, Daily, Take 1/2 tab daily for 7 days, then 1 tab daily thereafter.",
        "Naproxen-Esomeprazole 500-20 MG Tbec per DR tablet 1 tablet, Oral, 2 times a day"
      ],
      "procedures": [
        "nerve study",
        "carpal tunnel release"
      ],
      "labResults": [],
      "keyFindings": [
        "Patient presents with numbness Left Hand",
        "Positive Erkins of the left carpal tunnel, APB motor function intact",
        "Negative Tinel's over the cubital tunnel, no intrinsic wasting",
        "Watson's and provocative maneuvers negative for carpal instability",
        "Negative Finkelstein",
        "Negative thumb CMC grind",
        "otherwise neurovascular examination grossly intact",
        "X-rays negative for fracture"
      ]
    }
  ],
  "errors": [],
  "bySpecialty": {
    "primary_care": 1,
    "hand doc": 1
  },
  "byType": {
    "imaging_xray": 1,
    "office_visit": 1
  }
}